mainim/__init__.py
mainim/cst_parser.py
mainim/mvp.py
mainim-0.4.0.dist-info/METADATA
mainim-0.4.0.dist-info/WHEEL
mainim-0.4.0.dist-info/top_level.txt
mainim-0.4.0.dist-info/RECORD
