Metadata-Version: 2.4
Name: mAInim
Version: 0.4.0
Summary: Merging Manim & AI.
Requires-Python: >=3.13
Requires-Dist: manim>=0.19.0
Requires-Dist: latex>=0.7.0
Requires-Dist: libcst>=1.7.0
Requires-Dist: ipython>=8.31.0
Requires-Dist: requests
